{
	"rasa_nlu_data" : {
		"common_examples" : [
          {
              "text" : "find me data on the british economy",
              "intent" : "source_data",
              "entities" : [
                  {
                      "start" : 20,
                      "end" : 27,
                      "value" : "British",
                      "entity" : "tags"
                  },
                  {
                      "start" : 28,
                      "end" : 35,
                      "value" : "economy",
                      "entity" : "tags"
                  }

              ]
          },
          {
              "text" : "I want data regarding urban planning in London",
              "intent" : "source_data",
              "entities" : [
                  {
                      "start" : 22,
                      "end" : 36,
                      "value" : "urban planning",
                      "entity" : "tags"
                  },
                  {
                      "start" : 40,
                      "end" : 46,
                      "value" : "London",
                      "entity" : "tags"
                  }

              ]
          },
          {
              "text" : "search data about political discord",
              "intent" : "source_data",
              "entities" : [
                  {
                      "start" : 18,
                      "end" : 27,
                      "value" : "political",
                      "entity" : "tags"
                  },
                  {
                      "start" : 28,
                      "end" : 35,
                      "value" : "discord",
                      "entity" : "tags"
                  }

              ]
          },
          {
              "text" : "get information associated with population growth and food supply in underdeveloped countries",
              "intent" : "source_data",
              "entities" : [
                  {
                      "start" : 32,
                      "end" : 42,
                      "value" : "population",
                      "entity" : "tags"
                  },
                  {
                      "start" : 43,
                      "end" : 49,
                      "value" : "growth",
                      "entity" : "tags"
                  },
                  {
                      "start" : 54,
                      "end" : 58,
                      "value" : "food",
                      "entity" : "tags"
                  },
                  {
                      "start" : 59,
                      "end" : 65,
                      "value" : "supply",
                      "entity" : "tags"
                  },
                  {
                      "start" : 69,
                      "end" : 83,
                      "value" : "underdeveloped",
                      "entity" : "tags"
                  }

              ]
          },
          {
              "text" : "retrieve data about computer science",
              "intent" : "source_data",
              "entities" : [
                  {
                      "start" : 20,
                      "end" : 36,
                      "value" : "computer science",
                      "entity" : "tags"
                  }

              ]
          },
          {
              "text" : "need statistics about the urban domain",
              "intent" : "source_data",
              "entities" : [
                  {
                      "start" : 26,
                      "end" : 31,
                      "value" : "urban",
                      "entity" : "tags"
                  }

              ]
          },
          {
              "text" : "fetch figures concerning chinese news",
              "intent" : "source_data",
              "entities" : [
                  {
                      "start" : 25,
                      "end" : 32,
                      "value" : "chinese",
                      "entity" : "tags"
                  },
                  {
                      "start" : 33,
                      "end" : 37,
                      "value" : "news",
                      "entity" : "tags"
                  }

              ]
          },
          {
              "text" : "identify facts about ucl",
              "intent" : "source_data",
              "entities" : [
                  {
                      "start" : 21,
                      "end" : 24,
                      "value" : "University College London",
                      "entity" : "tags"
                  }

              ]
          },
          {
              "text" : "Im looking for details with regards to astronomy",
              "intent" : "source_data",
              "entities" : [
                  {
                      "start" : 39,
                      "end" : 48,
                      "value" : "astronomy",
                      "entity" : "tags"
                  }

              ]
          },
          {
              "text" : "Im looking for data",
              "intent" : "source_data"

          },
          {
              "text" : "find data for me",
              "intent" : "source_data"

          },
          {
              "text" : "i want to search for information",
              "intent" : "source_data"

          },
          {
              "text" : "i'm searching for data sources",
              "intent" : "source_data"

          },
          {
              "text" : "get me data",
              "intent" : "source_data"

          },
          {
              "text" : "im looking for some data",
              "intent" : "source_data"

          },
          {
              "text" : "can you get me data sources",
              "intent" : "source_data"

          },
          {
              "text" : "retrieve some relevant data sources for me",
              "intent" : "source_data"

          },
          {
              "text" : "fetch data",
              "intent" : "source_data"

          },
          {
              "text" : "get data",
              "intent" : "source_data"

          },
          {
              "text" : "source data",
              "intent" : "source_data"

          },
          {
              "text" : "search for data",
              "intent" : "source_data"

          },
          {
              "text" : "search for data source",
              "intent" : "source_data"

          },
          {
              "text" : "bring me some data",
              "intent" : "source_data"

          },
          {
              "text" : "british economy",
              "intent" : "source_data_inform_tags",
              "entities" : [
                  {
                      "start" : 0,
                      "end" : 7,
                      "value" : "British",
                      "entity" : "tags"
                  },
                  {
                      "start" : 8,
                      "end" : 15,
                      "value" : "economy",
                      "entity" : "tags"
                  }

              ]
          },
          {
              "text" : "urban planning",
              "intent" : "source_data_inform_tags",
              "entities" : [
                  {
                      "start" : 0,
                      "end" : 14,
                      "value" : "urban planning",
                      "entity" : "tags"
                  }

              ]
          },
          {
              "text" : "farming",
              "intent" : "source_data_inform_tags",
              "entities" : [
                  {
                      "start" : 0,
                      "end" : 7,
                      "value" : "farming",
                      "entity" : "tags"
                  }

              ]
          },
          {
              "text" : "London, built environment, transportation",
              "intent" : "source_data_inform_tags",
              "entities" : [
                  {
                      "start" : 0,
                      "end" : 6,
                      "value" : "London",
                      "entity" : "tags"
                  },
                  {
                      "start" : 8,
                      "end" : 25,
                      "value" : "built environment",
                      "entity" : "tags"
                  },
                  {
                      "start" : 27,
                      "end" : 41,
                      "value" : "transportation",
                      "entity" : "tags"
                  }

              ]
          },
          {
              "text" : "road networks, housing, transport",
              "intent" : "source_data_inform_tags",
              "entities" : [
                  {
                      "start" : 0,
                      "end" : 13,
                      "value" : "road networks",
                      "entity" : "tags"
                  },
                  {
                      "start" : 15,
                      "end" : 22,
                      "value" : "housing",
                      "entity" : "tags"
                  },
                  {
                      "start" : 24,
                      "end" : 33,
                      "value" : "transport",
                      "entity" : "tags"
                  }

              ]
          },
          {
              "text" : "university college london",
              "intent" : "source_data_inform_tags",
              "entities" : [
                  {
                      "start" : 0,
                      "end" : 10,
                      "value" : "university",
                      "entity" : "tags"
                  },
                  {
                      "start" : 11,
                      "end" : 18,
                      "value" : "college",
                      "entity" : "tags"
                  },
                  {
                      "start" : 19,
                      "end" : 25,
                      "value" : "London",
                      "entity" : "tags"
                  }

              ]
          },
          {
              "text" : "university college london, kings college london, imperial college london",
              "intent" : "source_data_inform_tags",
              "entities" : [
                  {
                      "start" : 0,
                      "end" : 25,
                      "value" : "University College London",
                      "entity" : "tags"
                  },
                  {
                      "start" : 27,
                      "end" : 47,
                      "value" : "Kings College London",
                      "entity" : "tags"
                  },
                  {
                      "start" : 49,
                      "end" : 72,
                      "value" : "Imperial College London",
                      "entity" : "tags"
                  }

              ]
          },
          {
              "text" : "ucl kcl icl",
              "intent" : "source_data_inform_tags",
              "entities" : [
                  {
                      "start" : 0,
                      "end" : 3,
                      "value" : "University College London",
                      "entity" : "tags"
                  },
                  {
                      "start" : 4,
                      "end" : 7,
                      "value" : "Kings College London",
                      "entity" : "tags"
                  },
                  {
                      "start" : 8,
                      "end" : 11,
                      "value" : "Imperial College London",
                      "entity" : "tags"
                  }

              ]
          },
          {
              "text" : "tags are rivers and plants",
              "intent" : "source_data_inform_tags",
              "entities" : [
                  {
                      "start" : 9,
                      "end" : 15,
                      "value" : "rivers",
                      "entity" : "tags"
                  },
                  {
                      "start" : 20,
                      "end" : 26,
                      "value" : "plants",
                      "entity" : "tags"
                  }

              ]
          },
          {
              "text" : "search terms are urban planning and population growth",
              "intent" : "source_data_inform_tags",
              "entities" : [
                  {
                      "start" : 17,
                      "end" : 31,
                      "value" : "urban planning",
                      "entity" : "tags"
                  },
                  {
                      "start" : 36,
                      "end" : 53,
                      "value" : "population growth",
                      "entity" : "tags"
                  }

              ]
          },
          {
              "text" : "query for terms related to financial data, markets and risk ",
              "intent" : "source_data_inform_tags",
              "entities" : [
                  {
                      "start" : 27,
                      "end" : 36,
                      "value" : "financial",
                      "entity" : "tags"
                  },
                  {
                      "start" : 43,
                      "end" : 50,
                      "value" : "markets",
                      "entity" : "tags"
                  },
                  {
                      "start" : 55,
                      "end" : 59,
                      "value" : "risk",
                      "entity" : "tags"
                  }

              ]
          },
          {
              "text" : "terms: construction congestion mobility housing",
              "intent" : "source_data_inform_tags",
              "entities" : [
                  {
                      "start" : 7,
                      "end" : 19,
                      "value" : "construction",
                      "entity" : "tags"
                  },
                  {
                      "start" : 20,
                      "end" : 30,
                      "value" : "congestion",
                      "entity" : "tags"
                  },
                  {
                      "start" : 31,
                      "end" : 39,
                      "value" : "mobility",
                      "entity" : "tags"
                  },
                  {
                      "start" : 40,
                      "end" : 47,
                      "value" : "housing",
                      "entity" : "tags"
                  }

              ]
          },
          {
              "text" : "queries: population growth, movement of people, census",
              "intent" : "source_data_inform_tags",
              "entities" : [
                  {
                      "start" : 9,
                      "end" : 26,
                      "value" : "population growth",
                      "entity" : "tags"
                  },
                  {
                      "start" : 28,
                      "end" : 46,
                      "value" : "movement of people",
                      "entity" : "tags"
                  },
                  {
                      "start" : 48,
                      "end" : 54,
                      "value" : "census",
                      "entity" : "tags"
                  }

              ]
          },
          {
              "text" : "parks forest",
              "intent" : "source_data_inform_tags",
              "entities" : [
                  {
                      "start" : 0,
                      "end" : 5,
                      "value" : "parks",
                      "entity" : "tags"
                  },
                  {
                      "start" : 6,
                      "end" : 12,
                      "value" : "forest",
                      "entity" : "tags"
                  }

              ]
          },
          {
              "text" : "Manchester",
              "intent" : "source_data_inform_tags",
              "entities" : [
                  {
                      "start" : 0,
                      "end" : 10,
                      "value" : "Manchester",
                      "entity" : "tags"
                  }

              ]
          },
          {
              "text" : "Scotland",
              "intent" : "source_data_inform_tags",
              "entities" : [
                  {
                      "start": 0,
                      "end": 8,
                      "value": "Scotland",
                      "entity": "tags"
                  }

              ]
          },
          {
              "text" : "United Kingdom, Europe, exports",
              "intent" : "source_data_inform_tags",
              "entities" : [
                  {
                      "start" : 0,
                      "end" : 14,
                      "value" : "United Kingdom",
                      "entity" : "tags"
                  },
                  {
                      "start" : 16,
                      "end" : 22,
                      "value" : "Europe",
                      "entity" : "tags"
                  },
                  {
                      "start" : 24,
                      "end" : 31,
                      "value" : "exports",
                      "entity" : "tags"
                  }

              ]
          },
          {
              "text" : "Brexit, exchange rate, value",
              "intent" : "source_data_inform_tags",
              "entities" : [
                  {
                      "start" : 0,
                      "end" : 6,
                      "value" : "Brexit",
                      "entity" : "tags"
                  },
                  {
                      "start" : 8,
                      "end" : 21,
                      "value" : "exchange rate",
                      "entity" : "tags"
                  }

              ]
          },
            {
                "text": "hey",
                "intent": "greet_start"
            },
            {
                "text": "hi",
                "intent": "greet_start"
            },
            {
                "text": "hello",
                "intent": "greet_start"
            },
            {
                "text": "yo",
                "intent": "greet_start"
            },
            {
                "text": "how's it going",
                "intent": "greet_start"
            },
            {
                "text": "what's up?",
                "intent": "greet_start"
            },
            {
                "text": "good morning",
                "intent": "greet_start"
            },
            {
                "text": "good evening",
                "intent": "greet_start"
            },
            {
                "text": "howdy",
                "intent": "greet_start"
            },
            {
                "text": "hey there",
                "intent": "greet_start"
            },
            {
                "text": "what's good",
                "intent": "greet_start"
            },
            {
                "text": "greetings",
                "intent": "greet_start"
            },
            {
                "text": "hi-ya",
                "intent": "greet_start"
            },
            {
                "text": "shalom",
                "intent": "greet_start"
            },
            {
                "text": "how are you",
                "intent": "greet_start"
            },
            {
                "text": "bye",
                "intent": "greet_end"
            },
            {
                "text": "goodbye",
                "intent": "greet_end"
            },
            {
                "text": "stop",
                "intent": "greet_end"
            },
            {
                "text": "end",
                "intent": "greet_end"
            },
            {
                "text": "farewell",
                "intent": "greet_end"
            },
            {
                "text": "Bye bye",
                "intent": "greet_end"
            },
            {
                "text": "have a good one",
                "intent": "greet_end"
            },
            {
                "text": "thanks",
                "intent": "greet_end"
            },
            {
                "text": "thank you",
                "intent": "greet_end"
            },
            {
                "text": "cheers",
                "intent": "greet_end"
            },
            {
                "text": "bless you",
                "intent": "greet_end"
            },
            {
                "text": "gracias",
                "intent": "greet_end"
            },
            {
                "text": "merci",
                "intent": "greet_end"
            },
            {
                "text": "yes",
                "intent": "affirm"
            },
            {
                "text": "yep",
                "intent": "affirm"
            },
            {
                "text": "yeah",
                "intent": "affirm"
            },
            {
                "text": "indeed",
                "intent": "affirm"
            },
            {
                "text": "that's right",
                "intent": "affirm"
            },
            {
                "text": "ok",
                "intent": "affirm"
            },
            {
                "text": "great",
                "intent": "affirm"
            },
            {
                "text": "right, thank you",
                "intent": "affirm"
            },
            {
                "text": "correct",
                "intent": "affirm"
            },
            {
                "text": "great choice",
                "intent": "affirm"
            },
            {
                "text": "sounds really good",
                "intent": "affirm"
            },
            {
                "text": "okay",
                "intent": "affirm"
            },
            {
                "text": "alright",
                "intent": "affirm"
            },
            {
                "text": "fine",
                "intent": "affirm"
            },
            {
                "text": "sure",
                "intent": "affirm"
            },
            {
                "text": "sure thing",
                "intent": "affirm"
            },
            {
                "text": "definitely",
                "intent": "affirm"
            },
            {
                "text": "no",
                "intent": "deny"
            },
            {
                "text": "nah",
                "intent": "deny"
            },
            {
                "text": "no thanks",
                "intent": "deny"
            },
            {
                "text": "negative",
                "intent": "deny"
            },
            {
                "text": "nae",
                "intent": "deny"
            },
            {
                "text": "nope",
                "intent": "deny"
            },
            {
                "text": "never",
                "intent": "deny"
            },
            {
                "text": "not really",
                "intent": "deny"
            },
            {
                "text": "no indeed",
                "intent": "deny"
            },
            {
                "text": "absolutely not",
                "intent": "deny"
            },
            {
                "text": "most certainly not",
                "intent": "deny"
            },
            {
                "text": "no way",
                "intent": "deny"
            },
            {
                "text": "that's enough",
                "intent": "deny"
            },
            {
              "text" : "find me data on the british economy",
              "intent" : "source_data",
              "entities" : [
                  {
                      "start" : 20,
                      "end" : 27,
                      "value" : "British",
                      "entity" : "tags"
                  },
                  {
                      "start" : 28,
                      "end" : 35,
                      "value" : "economy",
                      "entity" : "tags"
                  }

              ]
          },
          {
              "text" : "I want data regarding urban planning in London",
              "intent" : "source_data",
              "entities" : [
                  {
                      "start" : 22,
                      "end" : 36,
                      "value" : "urban planning",
                      "entity" : "tags"
                  },
                  {
                      "start" : 40,
                      "end" : 46,
                      "value" : "London",
                      "entity" : "tags"
                  }

              ]
          },
          {
              "text" : "search data about political discord",
              "intent" : "source_data",
              "entities" : [
                  {
                      "start" : 18,
                      "end" : 27,
                      "value" : "political",
                      "entity" : "tags"
                  },
                  {
                      "start" : 28,
                      "end" : 35,
                      "value" : "discord",
                      "entity" : "tags"
                  }

              ]
          },
          {
              "text" : "get information associated with population growth and food supply in underdeveloped countries",
              "intent" : "source_data",
              "entities" : [
                  {
                      "start" : 32,
                      "end" : 42,
                      "value" : "population",
                      "entity" : "tags"
                  },
                  {
                      "start" : 43,
                      "end" : 49,
                      "value" : "growth",
                      "entity" : "tags"
                  },
                  {
                      "start" : 54,
                      "end" : 58,
                      "value" : "food",
                      "entity" : "tags"
                  },
                  {
                      "start" : 59,
                      "end" : 65,
                      "value" : "supply",
                      "entity" : "tags"
                  },
                  {
                      "start" : 69,
                      "end" : 83,
                      "value" : "underdeveloped",
                      "entity" : "tags"
                  }

              ]
          },
          {
              "text" : "retrieve data about computer science",
              "intent" : "source_data",
              "entities" : [
                  {
                      "start" : 20,
                      "end" : 28,
                      "value" : "computer",
                      "entity" : "tags"
                  },
                  {
                      "start" : 29,
                      "end" : 36,
                      "value" : "science",
                      "entity" : "tags"
                  }

              ]
          },
          {
              "text" : "need statistics about the urban domain",
              "intent" : "source_data",
              "entities" : [
                  {
                      "start" : 26,
                      "end" : 31,
                      "value" : "urban",
                      "entity" : "tags"
                  }

              ]
          },
          {
              "text" : "fetch figures concerning chinese news",
              "intent" : "source_data",
              "entities" : [
                  {
                      "start" : 25,
                      "end" : 32,
                      "value" : "chinese",
                      "entity" : "tags"
                  },
                  {
                      "start" : 33,
                      "end" : 37,
                      "value" : "news",
                      "entity" : "tags"
                  }

              ]
          },
          {
              "text" : "identify facts about ucl",
              "intent" : "source_data",
              "entities" : [
                  {
                      "start" : 21,
                      "end" : 24,
                      "value" : "University College London",
                      "entity" : "tags"
                  }

              ]
          },
          {
              "text" : "Im looking for details with regards to astronomy",
              "intent" : "source_data",
              "entities" : [
                  {
                      "start" : 39,
                      "end" : 48,
                      "value" : "astronomy",
                      "entity" : "tags"
                  }

              ]
          },
          {
              "text" : "Im looking for data",
              "intent" : "source_data"

          },
          {
              "text" : "find data for me",
              "intent" : "source_data"

          },
          {
              "text" : "i want to search for information",
              "intent" : "source_data"

          },
          {
              "text" : "i'm searching for data sources",
              "intent" : "source_data"

          },
          {
              "text" : "get me data",
              "intent" : "source_data"

          },
          {
              "text" : "im looking for some data",
              "intent" : "source_data"

          },
          {
              "text" : "can you get me data sources",
              "intent" : "source_data"

          },
          {
              "text" : "retrieve some relevant data sources for me",
              "intent" : "source_data"

          },
          {
              "text" : "fetch data",
              "intent" : "source_data"

          },
          {
              "text" : "get data",
              "intent" : "source_data"

          },
          {
              "text" : "source data",
              "intent" : "source_data"

          },
          {
              "text" : "search for data",
              "intent" : "source_data"

          },
          {
              "text" : "search for data source",
              "intent" : "source_data"

          },
          {
              "text" : "bring me some data",
              "intent" : "source_data"

          },
          {
              "text" : "british economy",
              "intent" : "source_data_inform_tags",
              "entities" : [
                  {
                      "start" : 0,
                      "end" : 7,
                      "value" : "British",
                      "entity" : "tags"
                  },
                  {
                      "start" : 8,
                      "end" : 15,
                      "value" : "economy",
                      "entity" : "tags"
                  }

              ]
          },
          {
              "text" : "urban planning",
              "intent" : "source_data_inform_tags",
              "entities" : [
                  {
                      "start" : 0,
                      "end" : 14,
                      "value" : "urban planning",
                      "entity" : "tags"
                  }

              ]
          },
          {
              "text" : "farming",
              "intent" : "source_data_inform_tags",
              "entities" : [
                  {
                      "start" : 0,
                      "end" : 7,
                      "value" : "farming",
                      "entity" : "tags"
                  }

              ]
          },
          {
              "text" : "London, built environment, transportation",
              "intent" : "source_data_inform_tags",
              "entities" : [
                  {
                      "start" : 0,
                      "end" : 6,
                      "value" : "London",
                      "entity" : "tags"
                  },
                  {
                      "start" : 8,
                      "end" : 25,
                      "value" : "built environment",
                      "entity" : "tags"
                  },
                  {
                      "start" : 27,
                      "end" : 41,
                      "value" : "transportation",
                      "entity" : "tags"
                  }

              ]
          },
          {
              "text" : "road networks, housing, transport",
              "intent" : "source_data_inform_tags",
              "entities" : [
                  {
                      "start" : 0,
                      "end" : 13,
                      "value" : "road networks",
                      "entity" : "tags"
                  },
                  {
                      "start" : 15,
                      "end" : 22,
                      "value" : "housing",
                      "entity" : "tags"
                  },
                  {
                      "start" : 24,
                      "end" : 33,
                      "value" : "transport",
                      "entity" : "tags"
                  }

              ]
          },
          {
              "text" : "university college london",
              "intent" : "source_data_inform_tags",
              "entities" : [
                  {
                      "start" : 0,
                      "end" : 10,
                      "value" : "university",
                      "entity" : "tags"
                  },
                  {
                      "start" : 11,
                      "end" : 18,
                      "value" : "college",
                      "entity" : "tags"
                  },
                  {
                      "start" : 19,
                      "end" : 25,
                      "value" : "London",
                      "entity" : "tags"
                  }

              ]
          },
          {
              "text" : "university college london, kings college london, imperial college london",
              "intent" : "source_data_inform_tags",
              "entities" : [
                  {
                      "start" : 0,
                      "end" : 25,
                      "value" : "University College London",
                      "entity" : "tags"
                  },
                  {
                      "start" : 27,
                      "end" : 47,
                      "value" : "Kings College London",
                      "entity" : "tags"
                  },
                  {
                      "start" : 49,
                      "end" : 72,
                      "value" : "Imperial cCollege London",
                      "entity" : "tags"
                  }

              ]
          },
          {
              "text" : "ucl kcl icl",
              "intent" : "source_data_inform_tags",
              "entities" : [
                  {
                      "start" : 0,
                      "end" : 3,
                      "value" : "University College London",
                      "entity" : "tags"
                  },
                  {
                      "start" : 4,
                      "end" : 7,
                      "value" : "Kings College London",
                      "entity" : "tags"
                  },
                  {
                      "start" : 8,
                      "end" : 11,
                      "value" : "Imperial College London",
                      "entity" : "tags"
                  }

              ]
          },
          {
              "text" : "tags are rivers and plants",
              "intent" : "source_data_inform_tags",
              "entities" : [
                  {
                      "start" : 9,
                      "end" : 15,
                      "value" : "rivers",
                      "entity" : "tags"
                  },
                  {
                      "start" : 20,
                      "end" : 26,
                      "value" : "plants",
                      "entity" : "tags"
                  }

              ]
          },
          {
              "text" : "search terms are urban planning and population growth",
              "intent" : "source_data_inform_tags",
              "entities" : [
                  {
                      "start" : 17,
                      "end" : 31,
                      "value" : "urban planning",
                      "entity" : "tags"
                  },
                  {
                      "start" : 36,
                      "end" : 53,
                      "value" : "population growth",
                      "entity" : "tags"
                  }

              ]
          },
          {
              "text" : "query for terms related to financial data, markets and risk ",
              "intent" : "source_data_inform_tags",
              "entities" : [
                  {
                      "start" : 27,
                      "end" : 36,
                      "value" : "financial",
                      "entity" : "tags"
                  },
                  {
                      "start" : 43,
                      "end" : 50,
                      "value" : "markets",
                      "entity" : "tags"
                  },
                  {
                      "start" : 55,
                      "end" : 59,
                      "value" : "risk",
                      "entity" : "tags"
                  }

              ]
          },
          {
              "text" : "terms: construction congestion mobility housing",
              "intent" : "source_data_inform_tags",
              "entities" : [
                  {
                      "start" : 7,
                      "end" : 19,
                      "value" : "construction",
                      "entity" : "tags"
                  },
                  {
                      "start" : 20,
                      "end" : 30,
                      "value" : "congestion",
                      "entity" : "tags"
                  },
                  {
                      "start" : 31,
                      "end" : 39,
                      "value" : "mobility",
                      "entity" : "tags"
                  },
                  {
                      "start" : 40,
                      "end" : 47,
                      "value" : "housing",
                      "entity" : "tags"
                  }

              ]
          },
          {
              "text" : "queries: population growth, movement of people, census",
              "intent" : "source_data_inform_tags",
              "entities" : [
                  {
                      "start" : 9,
                      "end" : 26,
                      "value" : "population growth",
                      "entity" : "tags"
                  },
                  {
                      "start" : 28,
                      "end" : 46,
                      "value" : "movement of people",
                      "entity" : "tags"
                  },
                  {
                      "start" : 48,
                      "end" : 54,
                      "value" : "census",
                      "entity" : "tags"
                  }

              ]
          },
          {
              "text" : "parks forest",
              "intent" : "source_data_inform_tags",
              "entities" : [
                  {
                      "start" : 0,
                      "end" : 5,
                      "value" : "parks",
                      "entity" : "tags"
                  },
                  {
                      "start" : 6,
                      "end" : 12,
                      "value" : "forest",
                      "entity" : "tags"
                  }

              ]
          },
          {
              "text" : "Manchester",
              "intent" : "source_data_inform_tags",
              "entities" : [
                  {
                      "start" : 0,
                      "end" : 10,
                      "value" : "Manchester",
                      "entity" : "tags"
                  }

              ]
          },
          {
              "text" : "Scotland",
              "intent" : "source_data_inform_tags",
              "entities" : [
                  {
                      "start" : 0,
                      "end" : 8,
                      "value" : "Scotland",
                      "entity" : "tags"
                  }

              ]
          },
          {
              "text" : "United Kingdom, Europe, exports",
              "intent" : "source_data_inform_tags",
              "entities" : [
                  {
                      "start" : 0,
                      "end" : 14,
                      "value" : "United Kingdom",
                      "entity" : "tags"
                  },
                  {
                      "start" : 16,
                      "end" : 22,
                      "value" : "Europe",
                      "entity" : "tags"
                  },
                  {
                      "start" : 24,
                      "end" : 31,
                      "value" : "exports",
                      "entity" : "tags"
                  }

              ]
          },
          {
              "text" : "Brexit, exchange rate, value",
              "intent" : "source_data_inform_tags",
              "entities" : [
                  {
                      "start" : 0,
                      "end" : 6,
                      "value" : "Brexit",
                      "entity" : "tags"
                  },
                  {
                      "start" : 8,
                      "end" : 21,
                      "value" : "exchange rate",
                      "entity" : "tags"
                  }

              ]
          }

        ],
		"regex_features"	: [],
		"entity_synonyms"	:	[
            {
                "value" : "Hi",
                "synonyms" : ["hi"]
            }

        ]
	}
}